gitlab_mr.py
gitlab_mr-0.3.0.dist-info/DESCRIPTION.rst
gitlab_mr-0.3.0.dist-info/METADATA
gitlab_mr-0.3.0.dist-info/RECORD
gitlab_mr-0.3.0.dist-info/WHEEL
gitlab_mr-0.3.0.dist-info/entry_points.txt
gitlab_mr-0.3.0.dist-info/metadata.json
gitlab_mr-0.3.0.dist-info/top_level.txt
