Metadata-Version: 2.0
Name: gitlab-mr
Version: 0.3.0
Summary: Console utility to create gitlab merge requests.
Home-page: https://github.com/anti-social/gitlab-merge-request
Author: Alexander Koval
Author-email: kovalidis@gmail.com
License: Apache License 2.0
Keywords: git gitlab merge-request
Platform: UNKNOWN
Classifier: Development Status :: 3 - Alpha
Classifier: Intended Audience :: Developers
Classifier: License :: OSI Approved :: Apache Software License
Classifier: Operating System :: OS Independent
Classifier: Programming Language :: Python
Classifier: Environment :: Console
Classifier: Topic :: Software Development :: Version Control
Classifier: Topic :: Utilities
Requires-Dist: colorama (==0.3.9)
Requires-Dist: gitpython (==2.1.5)
Requires-Dist: python-gitlab (==1.0.0)
